MANIFEST.in
README.rst
setup.py
tox.ini
infi/__init__.py
infi.pyutils.egg-info/PKG-INFO
infi.pyutils.egg-info/SOURCES.txt
infi.pyutils.egg-info/dependency_links.txt
infi.pyutils.egg-info/namespace_packages.txt
infi.pyutils.egg-info/not-zip-safe
infi.pyutils.egg-info/requires.txt
infi.pyutils.egg-info/top_level.txt
infi/pyutils/__init__.py
infi/pyutils/__version__.py
infi/pyutils/contexts.py
infi/pyutils/decorators.py
infi/pyutils/enums.py
infi/pyutils/exceptions.py
infi/pyutils/function_signature.py
infi/pyutils/importing.py
infi/pyutils/iteration.py
infi/pyutils/keyed_object.py
infi/pyutils/lazy.py
infi/pyutils/method_map.py
infi/pyutils/misc.py
infi/pyutils/mixin.py
infi/pyutils/patch.py
infi/pyutils/predicates.py
infi/pyutils/python_compat.py
infi/pyutils/reference_counter.py
infi/pyutils/retry.py
infi/pyutils/functors/__init__.py
infi/pyutils/functors/always.py
infi/pyutils/functors/functor.py
infi/pyutils/functors/identity.py
infi/pyutils/functors/pass_.py
tests/__init__.py
tests/__init__.pyc
tests/test__contexts.py
tests/test__contexts.pyc
tests/test__decorators.py
tests/test__decorators.pyc
tests/test__enums.py
tests/test__enums.pyc
tests/test__function_signature.py
tests/test__function_signature.pyc
tests/test__keyed_objects.py
tests/test__keyed_objects.pyc
tests/test__lazy.py
tests/test__lazy.pyc
tests/test__method_map.py
tests/test__method_map.pyc
tests/test__mixin.py
tests/test__mixin.pyc
tests/test__patch.py
tests/test__patch.pyc
tests/test__readme_doctest.py
tests/test__readme_doctest.pyc
tests/test__recursive_getattr.py
tests/test__recursive_getattr.pyc
tests/test__reference_counter.py
tests/test__reference_counter.pyc
tests/test__reprify.py
tests/test__reprify.pyc
tests/test__retry.py
tests/test__retry.pyc
tests/test_utils.py
tests/test_utils.pyc