Metadata-Version: 1.1
Name: infi.pyutils
Version: 1.0.3
Summary: Misc. pure-python utilities
Home-page: UNKNOWN
Author: Rotem Yaari
Author-email: vmalloc@gmail.com
License: BSD
Platform: UNKNOWN
Classifier: Programming Language :: Python :: 2.6
Classifier: Programming Language :: Python :: 2.7
Classifier: Programming Language :: Python :: 3.3
